simplePackage3/__init__.py
simplePackage3/module3.py
simplePackage3-0.1.0.dist-info/METADATA
simplePackage3-0.1.0.dist-info/WHEEL
simplePackage3-0.1.0.dist-info/top_level.txt
simplePackage3-0.1.0.dist-info/RECORD
