Metadata-Version: 2.1
Name: simplePackage3
Version: 0.1.0
Summary: A example package
Home-page: https://www.google.com
Author: Alexey
Author-email: ashik2001@yandex.ru
License: UNKNOWN
Platform: UNKNOWN
Requires-Dist: numpy (==1.20.3)
